currency_converter/__init__.py
currency_converter/__main__.py
currency_converter/_version.py
currency_converter/currency_converter.py
currency_converter/eurofxref-hist.zip
currency_converter/eurofxref.csv
currencyconverter-0.18.14.dist-info/licenses/LICENSE
currencyconverter-0.18.14.dist-info/METADATA
currencyconverter-0.18.14.dist-info/WHEEL
currencyconverter-0.18.14.dist-info/entry_points.txt
currencyconverter-0.18.14.dist-info/top_level.txt
currencyconverter-0.18.14.dist-info/RECORD
