Metadata-Version: 2.4
Name: CurrencyConverter
Version: 0.18.14
Summary: A currency converter using the European Central Bank data.
Home-page: https://github.com/alexprengere/currencyconverter
Author: Alex Prengère
Author-email: alex.prengere@gmail.com
Classifier: Development Status :: 5 - Production/Stable
Classifier: Programming Language :: Python :: 3
Classifier: Programming Language :: Python :: 3 :: Only
Classifier: Programming Language :: Python :: Implementation :: CPython
Classifier: Programming Language :: Python :: Implementation :: PyPy
Requires-Python: >=3.9
License-File: LICENSE
Dynamic: license-file
